{
  "name": "lua@5.2",
  "full_name": "lua@5.2",
  "tap": null,
  "oldname": null,
  "oldnames": [],
  "aliases": [],
  "versioned_formulae": [],
  "desc": "Powerful, lightweight programming language",
  "license": "MIT",
  "homepage": "https://www.lua.org/",
  "versions": {
    "stable": "5.2.4",
    "head": null,
    "bottle": false
  },
  "urls": {
    "stable": {
      "url": "https://www.lua.org/ftp/lua-5.2.4.tar.gz",
      "tag": null,
      "revision": null,
      "using": null,
      "checksum": "b9e2e4aad6789b3b63a056d442f7b39f0ecfca3ae0f1fc0ae4e9614401b69f4b"
    }
  },
  "revision": 0,
  "version_scheme": 0,
  "bottle": {},
  "pour_bottle_only_if": null,
  "keg_only": true,
  "keg_only_reason": {
    "reason": ":versioned_formula",
    "explanation": ""
  },
  "options": [],
  "build_dependencies": [],
  "dependencies": [],
  "test_dependencies": [],
  "recommended_dependencies": [],
  "optional_dependencies": [],
  "uses_from_macos": [
    {
      "unzip": "build"
    }
  ],
  "uses_from_macos_bounds": [
    {}
  ],
  "requirements": [],
  "conflicts_with": [],
  "conflicts_with_reasons": [],
  "link_overwrite": [],
  "caveats": "You may also want luarocks:\n  brew install luarocks\n",
  "installed": [],
  "linked_keg": null,
  "pinned": false,
  "outdated": false,
  "deprecated": false,
  "deprecation_date": null,
  "deprecation_reason": null,
  "disabled": false,
  "disable_date": null,
  "disable_reason": null,
  "post_install_defined": false,
  "service": null,
  "tap_git_head": null,
  "ruby_source_path": null,
  "ruby_source_checksum": {
    "sha256": "af5fcd29c4576c0be140bf5891ff3441cceed1aa09c09e8f4f17d07f9fc66cc6"
  }
}
